rosalie/__init__.py
rosalie/simulator.py
rosalie/tests/__init__.py
rosalie/tests/test_simulator.py
rosalie/utils/helpers.py
rosalie/utils/input_checks.py
rosalie/utils/logger.py
rosalie/utils/result.py
rosalie-0.0.15.dist-info/METADATA
rosalie-0.0.15.dist-info/WHEEL
rosalie-0.0.15.dist-info/licenses/LICENSE
rosalie-0.0.15.dist-info/RECORD
