Metadata-Version: 2.1
Name: rosalie
Version: 0.0.15
Summary: A simple simulation tool to compare experiment evaluation methods.
Author-email: Fabian Gunzinger <fa.gunzinger@gmail.com>
License-File: LICENSE
Classifier: License :: OSI Approved :: MIT License
Classifier: Operating System :: OS Independent
Classifier: Programming Language :: Python :: 3
Requires-Python: >=3.7
